{"v":"5.6.9","fr":24,"ip":0,"op":58,"w":750,"h":500,"nm":"合成 1","ddd":0,"assets":[{"id":"0","w":360,"h":69,"u":"","p":"https://lzd-img-global.slatic.net/collect/faas2/galaxy-faas/lzd_interaction_oss/assets/55449e0d-6903-4421-8b96-40993aa4f1a1/0.png","e":1},{"id":"1","w":93,"h":115,"u":"","p":"https://lzd-img-global.slatic.net/collect/faas2/galaxy-faas/lzd_interaction_oss/assets/001421d4-29cf-4c81-ba02-fc6d194a838f/1.png","e":1},{"id":"2","w":387,"h":470,"u":"","p":"https://lzd-img-global.slatic.net/collect/faas2/galaxy-faas/lzd_interaction_oss/assets/6264f072-af7a-4bb9-aa23-22f24b7bbc79/2.png","e":1},{"id":"3","w":387,"h":470,"u":"","p":"https://lzd-img-global.slatic.net/collect/faas2/galaxy-faas/lzd_interaction_oss/assets/0ac67b0e-dbd6-454a-abcb-c942fe4294ce/3.png","e":1}],"layers":[{"ddd":0,"ind":1,"ty":4,"nm":"“Find us in channel icons”轮廓","parent":2,"sr":1,"ks":{"o":{"a":1,"k":[{"i":{"x":[0.833],"y":[0.833]},"o":{"x":[0.167],"y":[0.167]},"t":40,"s":[0],"e":[100]},{"t":48}],"ix":11},"r":{"a":0,"k":0,"ix":10},"p":{"a":0,"k":[43,42.5,0],"ix":2},"a":{"a":0,"k":[0,0,0],"ix":1},"s":{"a":0,"k":[100,100,100],"ix":6}},"ao":0,"shapes":[{"ty":"gr","it":[{"ind":0,"ty":"sh","ix":1,"ks":{"a":0,"k":{"i":[[0,0],[0,0],[0,0],[0,0],[0,0],[0,0],[0,0],[0,0],[0,0],[0,0]],"o":[[0,0],[0,0],[0,0],[0,0],[0,0],[0,0],[0,0],[0,0],[0,0],[0,0]],"v":[[2.069,0],[5.865,0],[5.865,-7.515],[11.757,-7.515],[11.757,-11.128],[5.865,-11.128],[5.865,-14.977],[13.38,-14.977],[13.38,-18.591],[2.069,-18.591]],"c":true},"ix":2},"nm":"F","hd":false},{"ty":"fl","c":{"a":0,"k":[0.067,0.067,0.067,1],"ix":4},"o":{"a":0,"k":100,"ix":5},"r":1,"bm":0,"nm":"填充 1","hd":false},{"ty":"tr","p":{"a":0,"k":[0,0],"ix":2},"a":{"a":0,"k":[0,0],"ix":1},"s":{"a":0,"k":[100,100],"ix":3},"r":{"a":0,"k":0,"ix":6},"o":{"a":0,"k":100,"ix":7},"sk":{"a":0,"k":0,"ix":4},"sa":{"a":0,"k":0,"ix":5},"nm":"变换"}],"nm":"F","np":3,"cix":2,"bm":0,"ix":1,"hd":false},{"ty":"gr","it":[{"ind":0,"ty":"sh","ix":1,"ks":{"a":0,"k":{"i":[[0,1.257],[1.283,0],[0,-1.257],[-1.231,0]],"o":[[0,-1.257],[-1.231,0],[0,1.257],[1.283,0]],"v":[[19.749,-17.517],[17.445,-19.795],[15.167,-17.517],[17.445,-15.239]],"c":true},"ix":2},"nm":"i","hd":false},{"ind":1,"ty":"sh","ix":2,"ks":{"a":0,"k":{"i":[[0,0],[0,0],[0,0],[0,0]],"o":[[0,0],[0,0],[0,0],[0,0]],"v":[[15.664,0],[19.251,0],[19.251,-13.092],[15.664,-13.092]],"c":true},"ix":2},"nm":"i","hd":false},{"ty":"mm","mm":1,"nm":"合并路径 1","hd":false},{"ty":"fl","c":{"a":0,"k":[0.067,0.067,0.067,1],"ix":4},"o":{"a":0,"k":100,"ix":5},"r":1,"bm":0,"nm":"填充 1","hd":false},{"ty":"tr","p":{"a":0,"k":[0,0],"ix":2},"a":{"a":0,"k":[0,0],"ix":1},"s":{"a":0,"k":[100,100],"ix":3},"r":{"a":0,"k":0,"ix":6},"o":{"a":0,"k":100,"ix":7},"sk":{"a":0,"k":0,"ix":4},"sa":{"a":0,"k":0,"ix":5},"nm":"变换"}],"nm":"i","np":5,"cix":2,"bm":0,"ix":2,"hd":false},{"ty":"gr","it":[{"ind":0,"ty":"sh","ix":1,"ks":{"a":0,"k":{"i":[[0,0],[0,0],[0,0],[-1.65,0],[0,-1.885],[0,0],[0,0],[0,0],[3.168,0],[0.681,-1.047],[0,0],[0,0]],"o":[[0,0],[0,0],[0,-2.514],[1.492,0],[0,0],[0,0],[0,0],[0,-3.404],[-1.702,0],[0,0],[0,0],[0,0]],"v":[[22.658,0],[26.245,0],[26.245,-6.389],[29.152,-10.107],[31.456,-7.07],[31.456,0],[35.043,0],[35.043,-7.672],[29.99,-13.38],[26.245,-11.6],[26.245,-13.092],[22.658,-13.092]],"c":true},"ix":2},"nm":"n","hd":false},{"ty":"fl","c":{"a":0,"k":[0.067,0.067,0.067,1],"ix":4},"o":{"a":0,"k":100,"ix":5},"r":1,"bm":0,"nm":"填充 1","hd":false},{"ty":"tr","p":{"a":0,"k":[0,0],"ix":2},"a":{"a":0,"k":[0,0],"ix":1},"s":{"a":0,"k":[100,100],"ix":3},"r":{"a":0,"k":0,"ix":6},"o":{"a":0,"k":100,"ix":7},"sk":{"a":0,"k":0,"ix":4},"sa":{"a":0,"k":0,"ix":5},"nm":"变换"}],"nm":"n","np":3,"cix":2,"bm":0,"ix":3,"hd":false},{"ty":"gr","it":[{"ind":0,"ty":"sh","ix":1,"ks":{"a":0,"k":{"i":[[0,-3.718],[-3.482,0],[-0.576,0.838],[0,0],[0,0],[0,0],[0,0],[0,0],[1.807,0]],"o":[[0,3.718],[1.807,0],[0,0],[0,0],[0,0],[0,0],[0,0],[-0.576,-0.838],[-3.482,0]],"v":[[37.394,-6.546],[43.548,0.288],[47.318,-1.466],[47.318,0],[50.905,0],[50.905,-19.638],[47.318,-19.638],[47.318,-11.626],[43.548,-13.38]],"c":true},"ix":2},"nm":"d","hd":false},{"ind":1,"ty":"sh","ix":2,"ks":{"a":0,"k":{"i":[[0,-2.042],[1.964,0],[0,2.042],[-1.964,0]],"o":[[0,2.042],[-1.964,0],[0,-2.042],[1.964,0]],"v":[[47.606,-6.546],[44.307,-2.985],[41.008,-6.546],[44.307,-10.107]],"c":true},"ix":2},"nm":"d","hd":false},{"ty":"mm","mm":1,"nm":"合并路径 1","hd":false},{"ty":"fl","c":{"a":0,"k":[0.067,0.067,0.067,1],"ix":4},"o":{"a":0,"k":100,"ix":5},"r":1,"bm":0,"nm":"填充 1","hd":false},{"ty":"tr","p":{"a":0,"k":[0,0],"ix":2},"a":{"a":0,"k":[0,0],"ix":1},"s":{"a":0,"k":[100,100],"ix":3},"r":{"a":0,"k":0,"ix":6},"o":{"a":0,"k":100,"ix":7},"sk":{"a":0,"k":0,"ix":4},"sa":{"a":0,"k":0,"ix":5},"nm":"变换"}],"nm":"d","np":5,"cix":2,"bm":0,"ix":4,"hd":false},{"ty":"gr","it":[{"ind":0,"ty":"sh","ix":1,"ks":{"a":0,"k":{"i":[[0,0],[-3.168,0],[-0.681,1.047],[0,0],[0,0],[0,0],[0,0],[0,0],[1.597,0],[0,1.964],[0,0],[0,0]],"o":[[0,3.482],[1.676,0],[0,0],[0,0],[0,0],[0,0],[0,0],[0,2.54],[-1.545,0],[0,0],[0,0],[0,0]],"v":[[60.045,-5.499],[64.968,0.288],[68.555,-1.492],[68.555,0],[72.142,0],[72.142,-13.092],[68.555,-13.092],[68.555,-6.703],[65.858,-2.985],[63.632,-6.101],[63.632,-13.092],[60.045,-13.092]],"c":true},"ix":2},"nm":"u","hd":false},{"ty":"fl","c":{"a":0,"k":[0.067,0.067,0.067,1],"ix":4},"o":{"a":0,"k":100,"ix":5},"r":1,"bm":0,"nm":"填充 1","hd":false},{"ty":"tr","p":{"a":0,"k":[0,0],"ix":2},"a":{"a":0,"k":[0,0],"ix":1},"s":{"a":0,"k":[100,100],"ix":3},"r":{"a":0,"k":0,"ix":6},"o":{"a":0,"k":100,"ix":7},"sk":{"a":0,"k":0,"ix":4},"sa":{"a":0,"k":0,"ix":5},"nm":"变换"}],"nm":"u","np":3,"cix":2,"bm":0,"ix":5,"hd":false},{"ty":"gr","it":[{"ind":0,"ty":"sh","ix":1,"ks":{"a":0,"k":{"i":[[0,2.461],[2.566,0.655],[0,0],[0,0.733],[-0.916,0],[-0.183,-0.995],[0,0],[2.88,0],[0,-2.252],[-2.278,-0.576],[0,0],[0,-0.681],[1.126,0],[0.131,1.152],[0,0],[-3.378,0]],"o":[[0,-2.042],[0,0],[-0.786,-0.183],[0,-0.628],[0.786,0],[0,0],[-0.209,-2.618],[-3.273,0],[0,1.911],[0,0],[1.152,0.288],[0,0.628],[-1.152,0],[0,0],[0.131,2.566],[3.168,0]],"v":[[86.016,-3.692],[82.377,-7.75],[80.072,-8.379],[78.58,-9.583],[80.125,-10.578],[81.853,-9.243],[85.466,-9.243],[80.177,-13.38],[74.914,-9.505],[78.239,-5.446],[80.701,-4.818],[82.35,-3.509],[80.648,-2.461],[78.37,-4.163],[74.626,-4.163],[80.544,0.288]],"c":true},"ix":2},"nm":"s","hd":false},{"ty":"fl","c":{"a":0,"k":[0.067,0.067,0.067,1],"ix":4},"o":{"a":0,"k":100,"ix":5},"r":1,"bm":0,"nm":"填充 1","hd":false},{"ty":"tr","p":{"a":0,"k":[0,0],"ix":2},"a":{"a":0,"k":[0,0],"ix":1},"s":{"a":0,"k":[100,100],"ix":3},"r":{"a":0,"k":0,"ix":6},"o":{"a":0,"k":100,"ix":7},"sk":{"a":0,"k":0,"ix":4},"sa":{"a":0,"k":0,"ix":5},"nm":"变换"}],"nm":"s","np":3,"cix":2,"bm":0,"ix":6,"hd":false},{"ty":"gr","it":[{"ind":0,"ty":"sh","ix":1,"ks":{"a":0,"k":{"i":[[0,1.257],[1.283,0],[0,-1.257],[-1.231,0]],"o":[[0,-1.257],[-1.231,0],[0,1.257],[1.283,0]],"v":[[98.529,-17.517],[96.225,-19.795],[93.947,-17.517],[96.225,-15.239]],"c":true},"ix":2},"nm":"i","hd":false},{"ind":1,"ty":"sh","ix":2,"ks":{"a":0,"k":{"i":[[0,0],[0,0],[0,0],[0,0]],"o":[[0,0],[0,0],[0,0],[0,0]],"v":[[94.444,0],[98.031,0],[98.031,-13.092],[94.444,-13.092]],"c":true},"ix":2},"nm":"i","hd":false},{"ty":"mm","mm":1,"nm":"合并路径 1","hd":false},{"ty":"fl","c":{"a":0,"k":[0.067,0.067,0.067,1],"ix":4},"o":{"a":0,"k":100,"ix":5},"r":1,"bm":0,"nm":"填充 1","hd":false},{"ty":"tr","p":{"a":0,"k":[0,0],"ix":2},"a":{"a":0,"k":[0,0],"ix":1},"s":{"a":0,"k":[100,100],"ix":3},"r":{"a":0,"k":0,"ix":6},"o":{"a":0,"k":100,"ix":7},"sk":{"a":0,"k":0,"ix":4},"sa":{"a":0,"k":0,"ix":5},"nm":"变换"}],"nm":"i","np":5,"cix":2,"bm":0,"ix":7,"hd":false},{"ty":"gr","it":[{"ind":0,"ty":"sh","ix":1,"ks":{"a":0,"k":{"i":[[0,0],[0,0],[0,0],[-1.65,0],[0,-1.885],[0,0],[0,0],[0,0],[3.168,0],[0.681,-1.047],[0,0],[0,0]],"o":[[0,0],[0,0],[0,-2.514],[1.492,0],[0,0],[0,0],[0,0],[0,-3.404],[-1.702,0],[0,0],[0,0],[0,0]],"v":[[101.438,0],[105.025,0],[105.025,-6.389],[107.932,-10.107],[110.236,-7.07],[110.236,0],[113.823,0],[113.823,-7.672],[108.77,-13.38],[105.025,-11.6],[105.025,-13.092],[101.438,-13.092]],"c":true},"ix":2},"nm":"n","hd":false},{"ty":"fl","c":{"a":0,"k":[0.067,0.067,0.067,1],"ix":4},"o":{"a":0,"k":100,"ix":5},"r":1,"bm":0,"nm":"填充 1","hd":false},{"ty":"tr","p":{"a":0,"k":[0,0],"ix":2},"a":{"a":0,"k":[0,0],"ix":1},"s":{"a":0,"k":[100,100],"ix":3},"r":{"a":0,"k":0,"ix":6},"o":{"a":0,"k":100,"ix":7},"sk":{"a":0,"k":0,"ix":4},"sa":{"a":0,"k":0,"ix":5},"nm":"变换"}],"nm":"n","np":3,"cix":2,"bm":0,"ix":8,"hd":false},{"ty":"gr","it":[{"ind":0,"ty":"sh","ix":1,"ks":{"a":0,"k":{"i":[[-0.707,3.011],[0,0],[1.519,0],[0,2.173],[-1.885,0],[-0.497,-1.178],[0,0],[3.613,0],[0,-3.797],[-3.98,0]],"o":[[0,0],[-0.497,1.178],[-1.885,0],[0,-2.173],[1.519,0],[0,0],[-0.707,-3.011],[-3.98,0],[0,3.797],[3.613,0]],"v":[[135.692,-5.001],[131.974,-5.001],[128.989,-2.959],[125.716,-6.546],[128.989,-10.133],[131.974,-8.091],[135.692,-8.091],[128.989,-13.38],[122.102,-6.546],[128.989,0.288]],"c":true},"ix":2},"nm":"c","hd":false},{"ty":"fl","c":{"a":0,"k":[0.067,0.067,0.067,1],"ix":4},"o":{"a":0,"k":100,"ix":5},"r":1,"bm":0,"nm":"填充 1","hd":false},{"ty":"tr","p":{"a":0,"k":[0,0],"ix":2},"a":{"a":0,"k":[0,0],"ix":1},"s":{"a":0,"k":[100,100],"ix":3},"r":{"a":0,"k":0,"ix":6},"o":{"a":0,"k":100,"ix":7},"sk":{"a":0,"k":0,"ix":4},"sa":{"a":0,"k":0,"ix":5},"nm":"变换"}],"nm":"c","np":3,"cix":2,"bm":0,"ix":9,"hd":false},{"ty":"gr","it":[{"ind":0,"ty":"sh","ix":1,"ks":{"a":0,"k":{"i":[[0,0],[0,0],[0,0],[-1.65,0],[0,-1.885],[0,0],[0,0],[0,0],[3.168,0],[0.681,-1.047],[0,0],[0,0]],"o":[[0,0],[0,0],[0,-2.514],[1.492,0],[0,0],[0,0],[0,0],[0,-3.404],[-1.702,0],[0,0],[0,0],[0,0]],"v":[[138.02,0],[141.607,0],[141.607,-6.389],[144.514,-10.107],[146.818,-7.07],[146.818,0],[150.405,0],[150.405,-7.672],[145.352,-13.38],[141.607,-11.6],[141.607,-19.638],[138.02,-19.638]],"c":true},"ix":2},"nm":"h","hd":false},{"ty":"fl","c":{"a":0,"k":[0.067,0.067,0.067,1],"ix":4},"o":{"a":0,"k":100,"ix":5},"r":1,"bm":0,"nm":"填充 1","hd":false},{"ty":"tr","p":{"a":0,"k":[0,0],"ix":2},"a":{"a":0,"k":[0,0],"ix":1},"s":{"a":0,"k":[100,100],"ix":3},"r":{"a":0,"k":0,"ix":6},"o":{"a":0,"k":100,"ix":7},"sk":{"a":0,"k":0,"ix":4},"sa":{"a":0,"k":0,"ix":5},"nm":"变换"}],"nm":"h","np":3,"cix":2,"bm":0,"ix":10,"hd":false},{"ty":"gr","it":[{"ind":0,"ty":"sh","ix":1,"ks":{"a":0,"k":{"i":[[0,-3.718],[-3.482,0],[-0.576,0.838],[0,0],[0,0],[0,0],[0,0],[0,0],[1.807,0]],"o":[[0,3.718],[1.807,0],[0,0],[0,0],[0,0],[0,0],[0,0],[-0.576,-0.838],[-3.482,0]],"v":[[152.756,-6.546],[158.91,0.288],[162.68,-1.466],[162.68,0],[166.267,0],[166.267,-13.092],[162.68,-13.092],[162.68,-11.626],[158.91,-13.38]],"c":true},"ix":2},"nm":"a","hd":false},{"ind":1,"ty":"sh","ix":2,"ks":{"a":0,"k":{"i":[[0,-2.042],[1.964,0],[0,2.042],[-1.964,0]],"o":[[0,2.042],[-1.964,0],[0,-2.042],[1.964,0]],"v":[[162.968,-6.546],[159.669,-2.985],[156.37,-6.546],[159.669,-10.107]],"c":true},"ix":2},"nm":"a","hd":false},{"ty":"mm","mm":1,"nm":"合并路径 1","hd":false},{"ty":"fl","c":{"a":0,"k":[0.067,0.067,0.067,1],"ix":4},"o":{"a":0,"k":100,"ix":5},"r":1,"bm":0,"nm":"填充 1","hd":false},{"ty":"tr","p":{"a":0,"k":[0,0],"ix":2},"a":{"a":0,"k":[0,0],"ix":1},"s":{"a":0,"k":[100,100],"ix":3},"r":{"a":0,"k":0,"ix":6},"o":{"a":0,"k":100,"ix":7},"sk":{"a":0,"k":0,"ix":4},"sa":{"a":0,"k":0,"ix":5},"nm":"变换"}],"nm":"a","np":5,"cix":2,"bm":0,"ix":11,"hd":false},{"ty":"gr","it":[{"ind":0,"ty":"sh","ix":1,"ks":{"a":0,"k":{"i":[[0,0],[0,0],[0,0],[-1.65,0],[0,-1.885],[0,0],[0,0],[0,0],[3.168,0],[0.681,-1.047],[0,0],[0,0]],"o":[[0,0],[0,0],[0,-2.514],[1.492,0],[0,0],[0,0],[0,0],[0,-3.404],[-1.702,0],[0,0],[0,0],[0,0]],"v":[[169.636,0],[173.223,0],[173.223,-6.389],[176.13,-10.107],[178.434,-7.07],[178.434,0],[182.021,0],[182.021,-7.672],[176.968,-13.38],[173.223,-11.6],[173.223,-13.092],[169.636,-13.092]],"c":true},"ix":2},"nm":"n","hd":false},{"ty":"fl","c":{"a":0,"k":[0.067,0.067,0.067,1],"ix":4},"o":{"a":0,"k":100,"ix":5},"r":1,"bm":0,"nm":"填充 1","hd":false},{"ty":"tr","p":{"a":0,"k":[0,0],"ix":2},"a":{"a":0,"k":[0,0],"ix":1},"s":{"a":0,"k":[100,100],"ix":3},"r":{"a":0,"k":0,"ix":6},"o":{"a":0,"k":100,"ix":7},"sk":{"a":0,"k":0,"ix":4},"sa":{"a":0,"k":0,"ix":5},"nm":"变换"}],"nm":"n","np":3,"cix":2,"bm":0,"ix":12,"hd":false},{"ty":"gr","it":[{"ind":0,"ty":"sh","ix":1,"ks":{"a":0,"k":{"i":[[0,0],[0,0],[0,0],[-1.65,0],[0,-1.885],[0,0],[0,0],[0,0],[3.168,0],[0.681,-1.047],[0,0],[0,0]],"o":[[0,0],[0,0],[0,-2.514],[1.492,0],[0,0],[0,0],[0,0],[0,-3.404],[-1.702,0],[0,0],[0,0],[0,0]],"v":[[185.21,0],[188.797,0],[188.797,-6.389],[191.704,-10.107],[194.008,-7.07],[194.008,0],[197.595,0],[197.595,-7.672],[192.542,-13.38],[188.797,-11.6],[188.797,-13.092],[185.21,-13.092]],"c":true},"ix":2},"nm":"n","hd":false},{"ty":"fl","c":{"a":0,"k":[0.067,0.067,0.067,1],"ix":4},"o":{"a":0,"k":100,"ix":5},"r":1,"bm":0,"nm":"填充 1","hd":false},{"ty":"tr","p":{"a":0,"k":[0,0],"ix":2},"a":{"a":0,"k":[0,0],"ix":1},"s":{"a":0,"k":[100,100],"ix":3},"r":{"a":0,"k":0,"ix":6},"o":{"a":0,"k":100,"ix":7},"sk":{"a":0,"k":0,"ix":4},"sa":{"a":0,"k":0,"ix":5},"nm":"变换"}],"nm":"n","np":3,"cix":2,"bm":0,"ix":13,"hd":false},{"ty":"gr","it":[{"ind":0,"ty":"sh","ix":1,"ks":{"a":0,"k":{"i":[[-0.786,2.645],[0,0],[1.257,0],[0.157,1.545],[0,0],[3.849,0],[0,-3.901],[-4.006,0]],"o":[[0,0],[-0.419,0.89],[-2.226,0],[0,0],[0.183,-4.923],[-3.98,0],[0,3.98],[3.325,0]],"v":[[213.51,-4.268],[209.765,-4.268],[206.99,-2.828],[203.455,-5.708],[213.667,-5.708],[206.833,-13.38],[199.946,-6.572],[206.806,0.288]],"c":true},"ix":2},"nm":"e","hd":false},{"ind":1,"ty":"sh","ix":2,"ks":{"a":0,"k":{"i":[[-1.65,0],[-0.445,-1.754],[0,0]],"o":[[1.231,0],[0,0],[0.34,-1.44]],"v":[[206.728,-10.474],[209.739,-8.065],[203.586,-8.065]],"c":true},"ix":2},"nm":"e","hd":false},{"ty":"mm","mm":1,"nm":"合并路径 1","hd":false},{"ty":"fl","c":{"a":0,"k":[0.067,0.067,0.067,1],"ix":4},"o":{"a":0,"k":100,"ix":5},"r":1,"bm":0,"nm":"填充 1","hd":false},{"ty":"tr","p":{"a":0,"k":[0,0],"ix":2},"a":{"a":0,"k":[0,0],"ix":1},"s":{"a":0,"k":[100,100],"ix":3},"r":{"a":0,"k":0,"ix":6},"o":{"a":0,"k":100,"ix":7},"sk":{"a":0,"k":0,"ix":4},"sa":{"a":0,"k":0,"ix":5},"nm":"变换"}],"nm":"e","np":5,"cix":2,"bm":0,"ix":14,"hd":false},{"ty":"gr","it":[{"ind":0,"ty":"sh","ix":1,"ks":{"a":0,"k":{"i":[[0,0],[0,0],[0,0],[0,0]],"o":[[0,0],[0,0],[0,0],[0,0]],"v":[[216.176,0],[219.763,0],[219.763,-19.638],[216.176,-19.638]],"c":true},"ix":2},"nm":"l","hd":false},{"ty":"fl","c":{"a":0,"k":[0.067,0.067,0.067,1],"ix":4},"o":{"a":0,"k":100,"ix":5},"r":1,"bm":0,"nm":"填充 1","hd":false},{"ty":"tr","p":{"a":0,"k":[0,0],"ix":2},"a":{"a":0,"k":[0,0],"ix":1},"s":{"a":0,"k":[100,100],"ix":3},"r":{"a":0,"k":0,"ix":6},"o":{"a":0,"k":100,"ix":7},"sk":{"a":0,"k":0,"ix":4},"sa":{"a":0,"k":0,"ix":5},"nm":"变换"}],"nm":"l","np":3,"cix":2,"bm":0,"ix":15,"hd":false},{"ty":"gr","it":[{"ind":0,"ty":"sh","ix":1,"ks":{"a":0,"k":{"i":[[0,1.257],[1.283,0],[0,-1.257],[-1.231,0]],"o":[[0,-1.257],[-1.231,0],[0,1.257],[1.283,0]],"v":[[233.183,-17.517],[230.879,-19.795],[228.601,-17.517],[230.879,-15.239]],"c":true},"ix":2},"nm":"i","hd":false},{"ind":1,"ty":"sh","ix":2,"ks":{"a":0,"k":{"i":[[0,0],[0,0],[0,0],[0,0]],"o":[[0,0],[0,0],[0,0],[0,0]],"v":[[229.098,0],[232.685,0],[232.685,-13.092],[229.098,-13.092]],"c":true},"ix":2},"nm":"i","hd":false},{"ty":"mm","mm":1,"nm":"合并路径 1","hd":false},{"ty":"fl","c":{"a":0,"k":[0.067,0.067,0.067,1],"ix":4},"o":{"a":0,"k":100,"ix":5},"r":1,"bm":0,"nm":"填充 1","hd":false},{"ty":"tr","p":{"a":0,"k":[0,0],"ix":2},"a":{"a":0,"k":[0,0],"ix":1},"s":{"a":0,"k":[100,100],"ix":3},"r":{"a":0,"k":0,"ix":6},"o":{"a":0,"k":100,"ix":7},"sk":{"a":0,"k":0,"ix":4},"sa":{"a":0,"k":0,"ix":5},"nm":"变换"}],"nm":"i","np":5,"cix":2,"bm":0,"ix":16,"hd":false},{"ty":"gr","it":[{"ind":0,"ty":"sh","ix":1,"ks":{"a":0,"k":{"i":[[-0.707,3.011],[0,0],[1.519,0],[0,2.173],[-1.885,0],[-0.497,-1.178],[0,0],[3.613,0],[0,-3.797],[-3.98,0]],"o":[[0,0],[-0.497,1.178],[-1.885,0],[0,-2.173],[1.519,0],[0,0],[-0.707,-3.011],[-3.98,0],[0,3.797],[3.613,0]],"v":[[248.844,-5.001],[245.126,-5.001],[242.141,-2.959],[238.868,-6.546],[242.141,-10.133],[245.126,-8.091],[248.844,-8.091],[242.141,-13.38],[235.254,-6.546],[242.141,0.288]],"c":true},"ix":2},"nm":"c","hd":false},{"ty":"fl","c":{"a":0,"k":[0.067,0.067,0.067,1],"ix":4},"o":{"a":0,"k":100,"ix":5},"r":1,"bm":0,"nm":"填充 1","hd":false},{"ty":"tr","p":{"a":0,"k":[0,0],"ix":2},"a":{"a":0,"k":[0,0],"ix":1},"s":{"a":0,"k":[100,100],"ix":3},"r":{"a":0,"k":0,"ix":6},"o":{"a":0,"k":100,"ix":7},"sk":{"a":0,"k":0,"ix":4},"sa":{"a":0,"k":0,"ix":5},"nm":"变换"}],"nm":"c","np":3,"cix":2,"bm":0,"ix":17,"hd":false},{"ty":"gr","it":[{"ind":0,"ty":"sh","ix":1,"ks":{"a":0,"k":{"i":[[0,3.823],[3.797,0],[0,-3.823],[-3.797,0]],"o":[[0,-3.823],[-3.797,0],[0,3.823],[3.797,0]],"v":[[264.081,-6.546],[257.194,-13.38],[250.308,-6.546],[257.194,0.288]],"c":true},"ix":2},"nm":"o","hd":false},{"ind":1,"ty":"sh","ix":2,"ks":{"a":0,"k":{"i":[[0,2.016],[-1.885,0],[0,-2.016],[1.885,0]],"o":[[0,-2.016],[1.885,0],[0,2.016],[-1.885,0]],"v":[[253.921,-6.546],[257.194,-10.029],[260.441,-6.546],[257.194,-3.064]],"c":true},"ix":2},"nm":"o","hd":false},{"ty":"mm","mm":1,"nm":"合并路径 1","hd":false},{"ty":"fl","c":{"a":0,"k":[0.067,0.067,0.067,1],"ix":4},"o":{"a":0,"k":100,"ix":5},"r":1,"bm":0,"nm":"填充 1","hd":false},{"ty":"tr","p":{"a":0,"k":[0,0],"ix":2},"a":{"a":0,"k":[0,0],"ix":1},"s":{"a":0,"k":[100,100],"ix":3},"r":{"a":0,"k":0,"ix":6},"o":{"a":0,"k":100,"ix":7},"sk":{"a":0,"k":0,"ix":4},"sa":{"a":0,"k":0,"ix":5},"nm":"变换"}],"nm":"o","np":5,"cix":2,"bm":0,"ix":18,"hd":false},{"ty":"gr","it":[{"ind":0,"ty":"sh","ix":1,"ks":{"a":0,"k":{"i":[[0,0],[0,0],[0,0],[-1.65,0],[0,-1.885],[0,0],[0,0],[0,0],[3.168,0],[0.681,-1.047],[0,0],[0,0]],"o":[[0,0],[0,0],[0,-2.514],[1.492,0],[0,0],[0,0],[0,0],[0,-3.404],[-1.702,0],[0,0],[0,0],[0,0]],"v":[[266.564,0],[270.151,0],[270.151,-6.389],[273.058,-10.107],[275.362,-7.07],[275.362,0],[278.949,0],[278.949,-7.672],[273.896,-13.38],[270.151,-11.6],[270.151,-13.092],[266.564,-13.092]],"c":true},"ix":2},"nm":"n","hd":false},{"ty":"fl","c":{"a":0,"k":[0.067,0.067,0.067,1],"ix":4},"o":{"a":0,"k":100,"ix":5},"r":1,"bm":0,"nm":"填充 1","hd":false},{"ty":"tr","p":{"a":0,"k":[0,0],"ix":2},"a":{"a":0,"k":[0,0],"ix":1},"s":{"a":0,"k":[100,100],"ix":3},"r":{"a":0,"k":0,"ix":6},"o":{"a":0,"k":100,"ix":7},"sk":{"a":0,"k":0,"ix":4},"sa":{"a":0,"k":0,"ix":5},"nm":"变换"}],"nm":"n","np":3,"cix":2,"bm":0,"ix":19,"hd":false},{"ty":"gr","it":[{"ind":0,"ty":"sh","ix":1,"ks":{"a":0,"k":{"i":[[0,2.461],[2.566,0.655],[0,0],[0,0.733],[-0.916,0],[-0.183,-0.995],[0,0],[2.88,0],[0,-2.252],[-2.278,-0.576],[0,0],[0,-0.681],[1.126,0],[0.131,1.152],[0,0],[-3.378,0]],"o":[[0,-2.042],[0,0],[-0.786,-0.183],[0,-0.628],[0.786,0],[0,0],[-0.209,-2.618],[-3.273,0],[0,1.911],[0,0],[1.152,0.288],[0,0.628],[-1.152,0],[0,0],[0.131,2.566],[3.168,0]],"v":[[292.664,-3.692],[289.025,-7.75],[286.72,-8.379],[285.228,-9.583],[286.773,-10.578],[288.501,-9.243],[292.114,-9.243],[286.825,-13.38],[281.562,-9.505],[284.887,-5.446],[287.349,-4.818],[288.998,-3.509],[287.296,-2.461],[285.018,-4.163],[281.274,-4.163],[287.192,0.288]],"c":true},"ix":2},"nm":"s","hd":false},{"ty":"fl","c":{"a":0,"k":[0.067,0.067,0.067,1],"ix":4},"o":{"a":0,"k":100,"ix":5},"r":1,"bm":0,"nm":"填充 1","hd":false},{"ty":"tr","p":{"a":0,"k":[0,0],"ix":2},"a":{"a":0,"k":[0,0],"ix":1},"s":{"a":0,"k":[100,100],"ix":3},"r":{"a":0,"k":0,"ix":6},"o":{"a":0,"k":100,"ix":7},"sk":{"a":0,"k":0,"ix":4},"sa":{"a":0,"k":0,"ix":5},"nm":"变换"}],"nm":"s","np":3,"cix":2,"bm":0,"ix":20,"hd":false}],"ip":0,"op":58,"st":0,"bm":0},{"ddd":0,"ind":2,"ty":2,"nm":"Text bubble","refId":"0","sr":1,"ks":{"o":{"a":1,"k":[{"i":{"x":[0.833],"y":[0.833]},"o":{"x":[0.167],"y":[0.167]},"t":40,"s":[0],"e":[100]},{"t":48}],"ix":11},"r":{"a":0,"k":0,"ix":10},"p":{"a":1,"k":[{"i":{"x":0.833,"y":0.833},"o":{"x":0.333,"y":0},"t":40,"s":[534,332,0],"e":[534,301.379,0],"to":[0,-4.906,0],"ti":[0,11.966,0]},{"i":{"x":0.667,"y":1},"o":{"x":0.167,"y":0.167},"t":44,"s":[534,301.379,0],"e":[534,283,0],"to":[0,-7.953,0],"ti":[0,3.261,0]},{"t":48}],"ix":2},"a":{"a":0,"k":[180,34.5,0],"ix":1},"s":{"a":0,"k":[100,100,100],"ix":6}},"ao":0,"ip":0,"op":58,"st":0,"bm":0},{"ddd":0,"ind":3,"ty":2,"nm":"Highlight","refId":"1","sr":1,"ks":{"o":{"a":1,"k":[{"i":{"x":[0.833],"y":[0.833]},"o":{"x":[0.167],"y":[0.167]},"t":0,"s":[0],"e":[0]},{"i":{"x":[0.833],"y":[0.833]},"o":{"x":[0.167],"y":[0.167]},"t":32,"s":[0],"e":[100]},{"t":33}],"ix":11},"r":{"a":0,"k":0,"ix":10},"p":{"a":1,"k":[{"i":{"x":0.833,"y":0.833},"o":{"x":0.167,"y":0.167},"t":0,"s":[301,339.5,0],"e":[301,339.5,0],"to":[0,0,0],"ti":[0,2.583,0]},{"i":{"x":0.833,"y":0.833},"o":{"x":0.333,"y":0},"t":32,"s":[301,339.5,0],"e":[301,331.749,0],"to":[0,-1.292,0],"ti":[0,3.23,0]},{"i":{"x":0.667,"y":1},"o":{"x":0.167,"y":0.167},"t":34,"s":[301,331.749,0],"e":[301,324,0],"to":[0,-3.229,0],"ti":[0,1.292,0]},{"t":40}],"ix":2},"a":{"a":0,"k":[46.5,57.5,0],"ix":1},"s":{"a":1,"k":[{"i":{"x":[0.833,0.833,0.833],"y":[0.833,0.833,0.833]},"o":{"x":[0.167,0.167,0.167],"y":[0.167,0.167,0.167]},"t":0,"s":[80.411,79.095,100],"e":[80.411,79.095,100]},{"i":{"x":[0.833,0.833,0.833],"y":[0.833,0.833,2.286]},"o":{"x":[0.333,0.333,0.333],"y":[0,0,0]},"t":32,"s":[80.411,79.095,100],"e":[90.206,89.547,100]},{"i":{"x":[0.667,0.667,0.667],"y":[1,1,1]},"o":{"x":[0.167,0.167,0.167],"y":[0.167,0.167,-1.286]},"t":34,"s":[90.206,89.547,100],"e":[100,100,100]},{"t":40}],"ix":6}},"ao":0,"ip":0,"op":58,"st":0,"bm":0},{"ddd":0,"ind":4,"ty":2,"nm":"Masked screen","parent":5,"refId":"2","sr":1,"ks":{"o":{"a":1,"k":[{"i":{"x":[0.833],"y":[1]},"o":{"x":[0.167],"y":[0]},"t":0,"s":[0],"e":[0]},{"i":{"x":[0.667],"y":[1]},"o":{"x":[0.333],"y":[0]},"t":32,"s":[0],"e":[100]},{"t":38}],"ix":11},"r":{"a":0,"k":0,"ix":10},"p":{"a":0,"k":[193.5,235,0],"ix":2},"a":{"a":0,"k":[193.5,235,0],"ix":1},"s":{"a":0,"k":[100,100,100],"ix":6}},"ao":0,"ip":0,"op":58,"st":0,"bm":0},{"ddd":0,"ind":5,"ty":2,"nm":"Screen","refId":"3","sr":1,"ks":{"o":{"a":0,"k":100,"ix":11},"r":{"a":0,"k":0,"ix":10},"p":{"a":1,"k":[{"i":{"x":0.833,"y":0.833},"o":{"x":0.333,"y":0},"t":0,"s":[375,735,0],"e":[375,523.014,0],"to":[0,-36.111,0],"ti":[0,89.931,0]},{"i":{"x":0.667,"y":1},"o":{"x":0.167,"y":0.167},"t":5.6,"s":[375,523.014,0],"e":[375,264,0],"to":[0,-105.566,0],"ti":[0,2.611,0]},{"i":{"x":0.833,"y":0.833},"o":{"x":0.167,"y":0.167},"t":14,"s":[375,264,0],"e":[375,263.488,0],"to":[0,-0.243,0],"ti":[0,0.105,0]},{"i":{"x":0.833,"y":0.833},"o":{"x":0.333,"y":0},"t":18,"s":[375,263.488,0],"e":[281.79,263.659,0],"to":[0,-0.322,0],"ti":[41.632,-0.25,0]},{"i":{"x":0.667,"y":1},"o":{"x":0.167,"y":0.167},"t":24,"s":[281.79,263.659,0],"e":[230,264,0],"to":[-28.172,0.169,0],"ti":[0,0,0]},{"t":32}],"ix":2},"a":{"a":0,"k":[193.5,235,0],"ix":1},"s":{"a":0,"k":[100,100,100],"ix":6}},"ao":0,"ip":0,"op":58,"st":0,"bm":0}],"markers":[],"_fr":24,"tiny":0.75}
